pirated_data/__init__.py
pirated_data/functionProvider.py
tests/test.py
pirated_data-0.0.2.dist-info/LICENSE
pirated_data-0.0.2.dist-info/METADATA
pirated_data-0.0.2.dist-info/WHEEL
pirated_data-0.0.2.dist-info/top_level.txt
pirated_data-0.0.2.dist-info/RECORD
