Metadata-Version: 2.1
Name: pirated-data
Version: 0.0.2
Summary: Generating sample user data like name, age, mobilenumber, aadharnumber etc for testing.
Author-email: Satyajit Behera <satyajit319@gmail.com>
Project-URL: Homepage, https://github.com/studyandmasti/pirated-data.git
Project-URL: Bug Tracker, https://github.com/studyandmasti/pirated-data/issuess
Classifier: Programming Language :: Python :: 3
Classifier: License :: OSI Approved :: MIT License
Classifier: Operating System :: OS Independent
Requires-Python: >=3.7
License-File: LICENSE
